mdbf/__init__.py
mdbf/bot.py
mdbf/cogs/__init__.py
mdbf/cogs/base.py
mdbf/utils.py
mdbf-0.4.1.dist-info/licenses/LICENSE
mdbf-0.4.1.dist-info/WHEEL
mdbf-0.4.1.dist-info/METADATA
mdbf-0.4.1.dist-info/RECORD
