Metadata-Version: 2.4
Name: mdbf
Version: 0.4.1
Summary: A Modular Discord Bot Framework based on pycord
Author: KiARC
Author-email: KiARC <kiarc@kiarc.win>
License-Expression: GPL-3.0
License-File: LICENSE
Requires-Dist: py-cord>=2.6.0,<3
Requires-Dist: pyyaml>=6.0.1,<7
Requires-Dist: toml>=0.10.2,<0.11
Requires-Python: ~=3.12.0
